lab2_basic/lab2_2_practice.sv
`timescale 1ns/1ps

module lab2_2_practice (
    input  logic       clk,
    input  logic       rst,
    input  logic       load,
    input  logic [7:0] N,
    input  logic       reload,
    output logic [7:0] out,
    output logic       done
);

    logic [7:0] prev_N;

    always_ff @ ( posedge clk ) begin
        done = 0;
        if ( rst ) 
            out <= 0;
        else if ( load ) begin
            prev_N <= N;
            out <= N;
        end
        else if ( reload ) begin
            out <= prev_NN;
        end
        else if ( out > 1 )
            out <= out - 1;
        else if ( out == 1 ) begin
            out <= out - 1;
            done <= 1;
        end
    end

endmodule

lab2_basic/lab2_2_practice_t.sv
module lab2_2_practice_tb;

    timeunit 1ns;
    timeprecision 1ps;

    localparam time CYCLE = 10ns;
    localparam int unsigned PATTERN_NUM = 32;

    logic clk;
    logic rst;
    logic load;
    logic [7:0] N;
    logic [7:0] out;
    logic reload;
    logic done;

    // Pattern layout: {rst, load, N[7:0], expected_out[7:0], expected_done}
    logic [18:0] patterns [0:PATTERN_NUM-1];
    logic expected_rst;
    logic expected_load;
    logic [7:0] expected_out;
    logic expected_done;

    int unsigned pattern_index;
    int unsigned pass_count;
    int unsigned failure_count = 0;
    integer pattern_file;
    bit timing_checks_enabled = 1'b0;
    realtime last_rising_edge = -1.0;

    lab2_2_practice dut (
        .clk(clk),
        .rst(rst),
        .load(load),
        .N(N),
        .out(out),
        .done(done),
        .reload(reload)
    );

    initial begin
        clk = 1'b0;
        forever #(CYCLE/2) clk = ~clk;
    end

    always @(posedge clk)
        last_rising_edge = $realtime;

    always @(out or done) begin
        #0;
        if (timing_checks_enabled && ($realtime != last_rising_edge)) begin
            failure_count = failure_count + 1;
            $display("<ERROR> out/done changed away from a rising edge at t=%0t", $time);
        end
    end

    initial begin
        #((PATTERN_NUM + 10) * CYCLE);
        $fatal(1, "Lab 2 Practice 2: FAIL (simulation timeout)");
    end

    initial begin
        rst = 1'b1;
        load = 1'b0;
        N = 8'd0;
        pass_count = 0;
        $display("Load pattern file %d", N);
        pattern_file = $fopen("pattern_B_practice.dat", "r");
        if (pattern_file == 0)
            $fatal(1, "Lab 2 Practice 2: FAIL (cannot open pattern_B_practice.dat; add it as a simulation source with Copy sources into project)");
        $fclose(pattern_file);
        for (pattern_index = 0; pattern_index < PATTERN_NUM; pattern_index++)
            patterns[pattern_index] = 'x;
        $readmemb("pattern_B_practice.dat", patterns);
        for (pattern_index = 0; pattern_index < PATTERN_NUM; pattern_index++) begin
            if ((^patterns[pattern_index]) === 1'bx)
                $fatal(1, "Lab 2 Practice 2: FAIL (pattern %0d is missing or contains X/Z; expected %0d complete binary patterns)", pattern_index, PATTERN_NUM);
        end

        @(posedge clk);
        #1ns;
        timing_checks_enabled = 1'b1;

        for (pattern_index = 0;
             pattern_index < PATTERN_NUM;
             pattern_index = pattern_index + 1) begin
            @(negedge clk);
            {expected_rst, expected_load, N, expected_out, expected_done}
                = patterns[pattern_index];
            rst = expected_rst;
            load = expected_load;

            @(posedge clk);
            #1ns;
            if ((out !== expected_out) || (done !== expected_done)) begin
                failure_count = failure_count + 1;
                $display("<ERROR> pattern %0d: rst=%b load=%b N=%0d out=%0d done=%b expected_out=%0d expected_done=%b",
                         pattern_index, rst, load, N, out, done,
                         expected_out, expected_done);
            end else begin
                pass_count = pass_count + 1;
            end
        end

        // Load a positive value, then assert reset away from a rising edge.
        @(negedge clk);
        rst = 1'b0;
        load = 1'b1;
        N = 8'd3;
        @(posedge clk);
        #1ns;
        if ((out !== 8'd3) || (done !== 1'b0)) begin
            failure_count = failure_count + 1;
            $display("<ERROR> reset probe setup: expected out=3 done=0, got out=%0d done=%b", out, done);
        end
        #1ns rst = 1'b1;
        @(negedge clk);
        load = 1'b0;
        @(posedge clk);
        #1ns;
        if ((out !== 8'd0) || (done !== 1'b0)) begin
            failure_count = failure_count + 1;
            $display("<ERROR> synchronous reset: expected out=0 done=0, got out=%0d done=%b", out, done);
        end

        if ((pass_count == PATTERN_NUM) && (failure_count == 0)) begin
            $display("========================================");
            $display("  Lab 2 Practice 2: PASS (%0d/%0d)",
                     pass_count, PATTERN_NUM);
            $display("========================================");
        end else begin
            $fatal(1, "Lab 2 Practice 2: FAIL (%0d/%0d patterns, %0d errors)",
                   pass_count, PATTERN_NUM, failure_count);
        end
        $finish;
    end

    initial begin
        $dumpfile("waveform.vcd");
        $dumpvars(0, lab2_2_practice_tb); // Replace with your top-level module/testbench name
    end

endmodule

lab2_basic/waveform.vcd
$date
	Mon Sep 21 23:00:01 2026
$end
$version
	Icarus Verilog
$end
$timescale
	1ps
$end
$scope module lab2_2_practice_tb $end
$var wire 8 ! out [7:0] $end
$var wire 1 " done $end
$var parameter 64 # CYCLE $end
$var parameter 32 $ PATTERN_NUM $end
$var reg 8 % N [7:0] $end
$var reg 1 & clk $end
$var reg 1 ' expected_done $end
$var reg 1 ( expected_load $end
$var reg 8 ) expected_out [7:0] $end
$var reg 1 * expected_rst $end
$var reg 1 + load $end
$var reg 1 , reload $end
$var reg 1 - rst $end
$var reg 32 . failure_count [31:0] $end
$var real 1 / last_rising_edge $end
$var reg 32 0 pass_count [31:0] $end
$var integer 32 1 pattern_file [31:0] $end
$var reg 32 2 pattern_index [31:0] $end
$var reg 1 3 timing_checks_enabled $end
$scope module dut $end
$var wire 8 4 N [7:0] $end
$var wire 1 & clk $end
$var wire 1 + load $end
$var wire 1 , reload $end
$var wire 1 - rst $end
$var reg 1 " done $end
$var reg 8 5 out [7:0] $end
$var reg 8 6 prev_N [7:0] $end
$upscope $end
$upscope $end
$enddefinitions $end
$comment Show the parameter values. $end
$dumpall
b100000 $
b1010 #
$end
#0
$dumpvars
bx 6
bx 5
b0 4
03
b100000 2
b10000000000000000000000000000011 1
b0 0
r-1 /
b0 .
1-
x,
0+
x*
bx )
x(
x'
0&
b0 %
x"
bx !
$end
#5000
b0 !
b0 5
0"
r5 /
1&
#6000
b0 2
13
#10000
1*
0(
b0 )
0'
0&
#15000
r15 /
1&
#16000
b1 2
b1 0
#20000
0&
#25000
r25 /
1&
#26000
b10 2
b10 0
#30000
0-
0*
0&
#35000
r35 /
1&
#36000
b11 2
b11 0
#40000
1+
1(
b11 %
b11 4
b11 )
0&
#45000
b11 !
b11 5
b11 6
r45 /
1&
#46000
b100 2
b100 0
#50000
0+
0(
b0 %
b0 4
b10 )
0&
#55000
b10 !
b10 5
r55 /
1&
#56000
b101 2
b101 0
#60000
b1 )
0&
#65000
b1 !
b1 5
r65 /
1&
#66000
b110 2
b110 0
#70000
b0 )
1'
0&
#75000
1"
b0 !
b0 5
r75 /
1&
#76000
b111 2
b111 0
#80000
0'
0&
#85000
0"
r85 /
1&
#86000
b1000 2
b1000 0
#90000
1+
1(
b101 %
b101 4
b101 )
0&
#95000
b101 !
b101 5
b101 6
r95 /
1&
#96000
b1001 2
b1001 0
#100000
0+
0(
b0 %
b0 4
b100 )
0&
#105000
b100 !
b100 5
r105 /
1&
#106000
b1010 2
b1010 0
#110000
b11 )
0&
#115000
b11 !
b11 5
r115 /
1&
#116000
b1011 2
b1011 0
#120000
b10 )
0&
#125000
b10 !
b10 5
r125 /
1&
#126000
b1100 2
b1100 0
#130000
b1 )
0&
#135000
b1 !
b1 5
r135 /
1&
#136000
b1101 2
b1101 0
#140000
b0 )
1'
0&
#145000
1"
b0 !
b0 5
r145 /
1&
#146000
b1110 2
b1110 0
#150000
0'
0&
#155000
r155 /
0"
1&
#156000
b1111 2
b1111 0
#160000
1+
1(
b1 %
b1 4
b1 )
0&
#165000
b1 !
b1 5
b1 6
r165 /
1&
#166000
b10000 2
b10000 0
#170000
0+
0(
b0 %
b0 4
b0 )
1'
0&
#175000
1"
b0 !
b0 5
r175 /
1&
#176000
b10001 2
b10001 0
#180000
0'
0&
#185000
0"
r185 /
1&
#186000
b10010 2
b10010 0
#190000
1+
1(
b1000 %
b1000 4
b1000 )
0&
#195000
b1000 !
b1000 5
b1000 6
r195 /
1&
#196000
b10011 2
b10011 0
#200000
0+
0(
b0 %
b0 4
b111 )
0&
#205000
b111 !
b111 5
r205 /
1&
#206000
b10100 2
b10100 0
#210000
b110 )
0&
#215000
b110 !
b110 5
r215 /
1&
#216000
b10101 2
b10101 0
#220000
b101 )
0&
#225000
b101 !
b101 5
r225 /
1&
#226000
b10110 2
b10110 0
#230000
b100 )
0&
#235000
b100 !
b100 5
r235 /
1&
#236000
b10111 2
b10111 0
#240000
b11 )
0&
#245000
b11 !
b11 5
r245 /
1&
#246000
b11000 2
b11000 0
#250000
b10 )
0&
#255000
b10 !
b10 5
r255 /
1&
#256000
b11001 2
b11001 0
#260000
b1 )
0&
#265000
b1 !
b1 5
r265 /
1&
#266000
b11010 2
b11010 0
#270000
b0 )
1'
0&
#275000
1"
b0 !
b0 5
r275 /
1&
#276000
b11011 2
b11011 0
#280000
0'
0&
#285000
0"
r285 /
1&
#286000
b11100 2
b11100 0
#290000
0&
#295000
r295 /
1&
#296000
b11101 2
b11101 0
#300000
0&
#305000
r305 /
1&
#306000
b11110 2
b11110 0
#310000
0&
#315000
r315 /
1&
#316000
b11111 2
b11111 0
#320000
0&
#325000
r325 /
1&
#326000
b100000 2
b100000 0
#330000
b11 %
b11 4
1+
0&
#335000
b11 !
b11 5
b11 6
r335 /
1&
#337000
1-
#340000
0+
0&
#345000
b0 !
b0 5
r345 /
1&
