lab1/practice_2.sv
`timescale 1ns/100ps

module practice_2 (
    input  logic G,
    input  logic D,
    output wire P,
    output wire Pn
);
    wire nandD, nandG, nand1, nand2, notD;
    not (notD, D);
    nand (nandD, G, D);
    nand (nandG, notD, G);
    nand (P, nandD, Pn);
    nand (Pn, nandG, P);

endmodule

lab1/practice_2_t.sv
`timescale 1ns/100ps

module practice_2_t();
initial begin
        $dumpfile("waveform.vcd");
        $dumpvars(0, practice_2_t); // Replace 'top' with your top module name
    end
/* verilator lint_off UNOPTFLAT */
    logic G, D;
    /* verilator lint_off UNOPTFLAT */
    logic P, Pn, expected_P, expected_Pn;

/* verilator lint_off UNOPTFLAT */
    //====================================
    // TODO
    // Connect your practice_2 module here with "G", "D", "P", and "Pn".
    // Please connect it by port name but not order
    /* verilator lint_off UNOPTFLAT */
    practice_2 p2(.G(G), .D(D), .P(P), .Pn(Pn));

    //====================================

    golden_2 golden_latch(.G(G), .D(D), .P(expected_P), .Pn(expected_Pn));

    parameter LEN = 9;
    logic [LEN-1:0] G_pattern = 9'b011001100; // Gate input G: 0 -> 1 -> 1 -> 0 -> 0 -> 1 -> 1 -> 0 -> 0
    logic [LEN-1:0] D_pattern = 9'b001101001; // Data input D: 0 -> 0 -> 1 -> 1 -> 0 -> 1 -> 0 -> 0 -> 1

    logic [LEN-1:0] student_Ps;
    logic [LEN-1:0] student_Pns;
    logic [LEN-1:0] golden_Ps;
    logic [LEN-1:0] golden_Pns;
    integer error_count, i;

    initial begin
        error_count = 0;
        for (i = 0; i < LEN; i = i + 1) begin
            G = G_pattern[i];
            D = D_pattern[i];

            // Check the outputs
            #1; // small delay to ensure output is ready
            student_Ps[i] = P;
            student_Pns[i] = Pn;
            golden_Ps[i] = expected_P;
            golden_Pns[i] = expected_Pn;
            if (P !== expected_P) error_count = error_count + 1;
            if (Pn !== expected_Pn) error_count = error_count + 1;

            #9;
        end

        if (error_count === 0) $display("[SUCCESS]: All tests passed successfully!");
        else begin
            $display("[ERROR]: There were %0d errors.", error_count);

            $write("     Gate input G: %b", G_pattern[0]);
            for (i = 1; i < LEN; i = i + 1) $write(" -> %b", G_pattern[i]);
            $write("\n");

            $write("     Data input D: %b", D_pattern[0]);
            for (i = 1; i < LEN; i = i + 1) $write(" -> %b", D_pattern[i]);
            $write("\n");

            $write("    Your output P: %b", student_Ps[0]);
            for (i = 1; i < LEN; i = i + 1) $write(" -> %b", student_Ps[i]);
            $write("\n");

            $write("   Your output Pn: %b", student_Pns[0]);
            for (i = 1; i < LEN; i = i + 1) $write(" -> %b", student_Pns[i]);
            $write("\n");

            $write(" Correct output P: %b", golden_Ps[0]);
            for (i = 1; i < LEN; i = i + 1) $write(" -> %b", golden_Ps[i]);
            $write("\n");

            $write("Correct output Pn: %b", golden_Pns[0]);
            for (i = 1; i < LEN; i = i + 1) $write(" -> %b", golden_Pns[i]);
            $write("\n");
        end
        $finish;
    end

    

endmodule

module golden_2(
    input  logic G,
    input  logic D,
    output logic P,
    output logic Pn
);
    assign Pn = ~P;
    always @(G or D) if (G) P <= D;
endmodule

lab1/waveform.vcd
$date
	Tue Sep 15 11:17:43 2026
$end
$version
	Icarus Verilog
$end
$timescale
	100ps
$end
$scope module practice_2_t $end
$var wire 1 ! expected_Pn $end
$var wire 1 " expected_P $end
$var wire 1 # Pn $end
$var wire 1 $ P $end
$var parameter 32 % LEN $end
$var reg 1 & D $end
$var reg 9 ' D_pattern [8:0] $end
$var reg 1 ( G $end
$var reg 9 ) G_pattern [8:0] $end
$var reg 9 * golden_Pns [8:0] $end
$var reg 9 + golden_Ps [8:0] $end
$var reg 9 , student_Pns [8:0] $end
$var reg 9 - student_Ps [8:0] $end
$var integer 32 . error_count [31:0] $end
$var integer 32 / i [31:0] $end
$scope module golden_latch $end
$var wire 1 & D $end
$var wire 1 ( G $end
$var wire 1 ! Pn $end
$var reg 1 " P $end
$upscope $end
$scope module p2 $end
$var wire 1 & D $end
$var wire 1 ( G $end
$var wire 1 $ P $end
$var wire 1 # Pn $end
$var wire 1 0 nandD $end
$var wire 1 1 nandG $end
$var wire 1 2 notD $end
$upscope $end
$upscope $end
$enddefinitions $end
$comment Show the parameter values. $end
$dumpall
b1001 %
$end
#0
$dumpvars
02
11
10
b0 /
b0 .
bx -
bx ,
bx +
bx *
b11001100 )
0(
b1101001 '
1&
x$
x#
x"
x!
$end
#100
12
0&
b1 /
#200
1!
0"
0$
1#
01
1(
b10 /
#210
bx1xx *
bx0xx +
bx1xx ,
bx0xx -
#300
0!
1"
0#
11
1$
02
00
1&
b11 /
#310
bx01xx *
bx10xx +
bx01xx ,
bx10xx -
#400
12
10
0&
0(
b100 /
#410
bx001xx *
bx110xx +
bx001xx ,
bx110xx -
#500
02
1&
b101 /
#510
bx0001xx *
bx1110xx +
bx0001xx ,
bx1110xx -
#600
00
1(
b110 /
#610
bx00001xx *
bx11110xx +
bx00001xx ,
bx11110xx -
#700
1!
0"
0$
1#
01
12
10
0&
b111 /
#710
bx100001xx *
bx011110xx +
bx100001xx ,
bx011110xx -
#800
11
0(
b1000 /
#810
b1100001xx *
b11110xx +
b1100001xx ,
b11110xx -
#900
b1001 /
